minecrypto/__init__.py
minecrypto/minecryptotest.py
minecrypto-0.0.1.dist-info/LICENSE
minecrypto-0.0.1.dist-info/METADATA
minecrypto-0.0.1.dist-info/WHEEL
minecrypto-0.0.1.dist-info/top_level.txt
minecrypto-0.0.1.dist-info/RECORD
