Metadata-Version: 2.1
Name: minecrypto
Version: 0.0.1
Summary: minecrypto is a mining module
Home-page: https://github.com/catdogmat/mine
Author: beano09
Author-email: pif12345677@gmail.com
License: UNKNOWN
Project-URL: Bug Tracker, https://github.com/catdogmat/mine/issues
Platform: UNKNOWN
Classifier: Programming Language :: Python :: 3
Classifier: License :: OSI Approved :: MIT License
Classifier: Operating System :: OS Independent
Requires-Python: >=3.6
License-File: LICENSE
